setup.cfg
setup.py
pipsearch/__init__.py
pipsearch/api.py
pipsearch.egg-info/PKG-INFO
pipsearch.egg-info/SOURCES.txt
pipsearch.egg-info/dependency_links.txt
pipsearch.egg-info/entry_points.txt
pipsearch.egg-info/not-zip-safe
pipsearch.egg-info/requires.txt
pipsearch.egg-info/top_level.txt