Metadata-Version: 1.1
Name: pipsearch
Version: 2.9
Summary: Search pypi modules
Home-page: https://github.com/biggydbs/pipsearch
Author: Hitesh Jain
Author-email: jain.hitesh30695@gmail.com
License: UNKNOWN
Download-URL: https://github.com/biggydbs/pipsearch/archive/2.tar.gz
Platform: UNKNOWN
